test_transcribe/__init__.py
test_transcribe/blob/__init__.py
test_transcribe/blob/blob.py
test_transcribe/fixtures/__init__.py
test_transcribe/fixtures/azure_languages.py
test_transcribe/fixtures/azure_transcribe_states.py
test_transcribe/transcribe/__init__.py
test_transcribe/transcribe/transcribe.py
test_transcribe-6.2.dist-info/LICENSE
test_transcribe-6.2.dist-info/METADATA
test_transcribe-6.2.dist-info/WHEEL
test_transcribe-6.2.dist-info/entry_points.txt
test_transcribe-6.2.dist-info/top_level.txt
test_transcribe-6.2.dist-info/RECORD
