Metadata-Version: 2.1
Name: test-transcribe
Version: 6.2
Summary: ESRP Release is a pathway to many abilities some consider to be, unnatural.
Home-page: https://github.com/DCDie/azure-transcribe
Author: Vishal Jaishankar, Shesh Rao, Arun Gupta, Priyankar Thaikur
Author-email: vijaisha@microsoft.com, shmallip@microsoft.com, arugupta@microsoft.com, prthaku@microsoft.com
Maintainer: Vishal Jaishankar, Shesh Rao, Arun Gupta
Maintainer-email: shmallip@microsoft.com, vijaisha@microsoft.com, arugupta@microsoft.com
License: This is a new licemse for 5.0
Project-URL: Bug Tracker, https://github.com/DCDie/azure-transcribe/issues
Platform: windows
Platform: linux
Classifier: Programming Language :: Python :: 3
Requires-Python: >=3.6
License-File: LICENSE
Requires-Dist: azure-storage-blob (==12.12.0)
Requires-Dist: requests (>=2.23.0)
Provides-Extra: pdf
Requires-Dist: ReportLab (>=1.2) ; extra == 'pdf'
Requires-Dist: RXP ; extra == 'pdf'
